ariksa_policy_cli/app/core/settings.py
ariksa_policy_cli/app/main.py
ariksa_policy_cli/app/modules/utils/query.py
ariksa_policy_cli/app/modules/utils/send_request.py
ariksa_policy_cli/app/schemas/__init__.py
ariksa_policy_cli/app/schemas/resource.py
ariksa_policy_cli-0.1.16.dist-info/METADATA
ariksa_policy_cli-0.1.16.dist-info/WHEEL
ariksa_policy_cli-0.1.16.dist-info/entry_points.txt
ariksa_policy_cli-0.1.16.dist-info/RECORD
